setup.py
src/futuregrid_move/__init__.py
src/futuregrid_move.egg-info/PKG-INFO
src/futuregrid_move.egg-info/SOURCES.txt
src/futuregrid_move.egg-info/dependency_links.txt
src/futuregrid_move.egg-info/not-zip-safe
src/futuregrid_move.egg-info/requires.txt
src/futuregrid_move.egg-info/top_level.txt
src/futuregrid_move/rain/__init__.py
src/futuregrid_move/rain/move/EucaService.py
src/futuregrid_move/rain/move/FGMoveShell.py
src/futuregrid_move/rain/move/Fabric.py
src/futuregrid_move/rain/move/HPCService.py
src/futuregrid_move/rain/move/NimbusService.py
src/futuregrid_move/rain/move/OpenNebulaService.py
src/futuregrid_move/rain/move/OpenStackService.py
src/futuregrid_move/rain/move/RainMoveClient.py
src/futuregrid_move/rain/move/RainMoveClientConf.py
src/futuregrid_move/rain/move/RainMoveServer.py
src/futuregrid_move/rain/move/RainMoveServerConf.py
src/futuregrid_move/rain/move/RainMoveServerSites.py
src/futuregrid_move/rain/move/Resource.py
src/futuregrid_move/rain/move/__init__.py
src/futuregrid_move/rain/move/fg-move
src/futuregrid_move/rain/move/test.py
src/futuregrid_move/utils/FGAuth.py
src/futuregrid_move/utils/FGTypes.py
src/futuregrid_move/utils/__init__.py
src/futuregrid_move/utils/fgLog.py