Metadata-Version: 1.0
Name: futuregrid-move
Version: 0.1
Summary: FutureGrid Rain Move is a software to move resources between infrastructures. This will be part of Rain.
Home-page: http://futuregrid.github.com/rain_move/index.html
Author: Javier Diaz, Fugang Wang, Koji Tanaka, Gregor von Laszewski
Author-email: javier.diazmontes@gmail.com
License: Apache Software License
Keywords: Cloud,Grid,HPC
Platform: UNKNOWN
Classifier: Development Status :: 4 - Beta
Classifier: Intended Audience :: Developers
Classifier: Intended Audience :: System Administrators
Classifier: License :: OSI Approved :: Apache Software License
Classifier: Operating System :: OS Independent
Classifier: Programming Language :: Python
Classifier: Topic :: Software Development :: Libraries :: Python Modules
Classifier: Topic :: Scientific/Engineering
Classifier: Topic :: System :: Distributed Computing
